topicnetwork/__init__.py
topicnetwork-0.1.4.dist-info/METADATA
topicnetwork-0.1.4.dist-info/RECORD
topicnetwork-0.1.4.dist-info/WHEEL
topicnetwork-0.1.4.dist-info/top_level.txt
