Metadata-Version: 2.1
Name: topicnetwork
Version: 0.1.4
Summary: Topic modeling with text networks
Home-page: http://github.com/michal-pikusa/topic-network
Author: Michal Pikusa
Author-email: pikusa.michal@gmail.com
License: MIT
Keywords: topic network community detection
Platform: UNKNOWN
Classifier: Development Status :: 3 - Alpha
Classifier: License :: OSI Approved :: MIT License
Classifier: Programming Language :: Python :: 3.6
Classifier: Topic :: Text Processing :: Linguistic
Requires-Dist: networkx
Requires-Dist: nltk
